satcatalogquery/Const.py
satcatalogquery/__init__.py
satcatalogquery/classes.py
satcatalogquery/data_download.py
satcatalogquery/data_prepare.py
satcatalogquery/query.py
satcatalogquery/try_download.py
satcatalogquery-0.2.5.dist-info/licenses/LICENSE
satcatalogquery-0.2.5.dist-info/METADATA
satcatalogquery-0.2.5.dist-info/WHEEL
satcatalogquery-0.2.5.dist-info/top_level.txt
satcatalogquery-0.2.5.dist-info/RECORD
