Metadata-Version: 2.4
Name: satcatalogquery
Version: 0.2.5
Summary: A package for querying orbital and geometric information of spatial objects
Home-page: https://github.com/lcx366/SATQUERY
Author: Chunxiao Li
Author-email: lcx366@126.com
License: MIT
Keywords: DISCOS,CelesTrak,SpaceTrack,Space Debris
Classifier: Development Status :: 4 - Beta
Classifier: Intended Audience :: Education
Classifier: Intended Audience :: Science/Research
Classifier: Programming Language :: Python :: 3.10
Classifier: Programming Language :: Python :: 3.11
Classifier: Programming Language :: Python :: 3.12
Classifier: License :: OSI Approved :: MIT License
Requires-Python: >=3.10
License-File: LICENSE
Requires-Dist: spacetrack
Requires-Dist: numpy>=1.21.2
Requires-Dist: matplotlib
Requires-Dist: pandas
Requires-Dist: wget
Requires-Dist: colorama
Dynamic: author
Dynamic: author-email
Dynamic: classifier
Dynamic: description
Dynamic: description-content-type
Dynamic: home-page
Dynamic: keywords
Dynamic: license
Dynamic: license-file
Dynamic: requires-dist
Dynamic: requires-python
Dynamic: summary
